pylmdb/__init__.py
pylmdb/pylmdb.py
pylmdb/tools.py
sindre_lmdb-2023.9.11.dist-info/METADATA
sindre_lmdb-2023.9.11.dist-info/WHEEL
sindre_lmdb-2023.9.11.dist-info/top_level.txt
sindre_lmdb-2023.9.11.dist-info/RECORD
