Metadata-Version: 2.1
Name: sindre-lmdb
Version: 2023.9.11
Summary: simple lmdb wrapper
Home-page: https://github.com/SindreYang/pylmdb
Author: SindreYang
License: GNU General Public License v3.0
Requires-Dist: numpy
Requires-Dist: psutil
Requires-Dist: lmdb
Requires-Dist: msgpack
